mcp_formio_server/__init__.py
mcp_formio_server/config.py
mcp_formio_server/exceptions.py
mcp_formio_server/main.py
mcp_formio_server/api/__init__.py
mcp_formio_server/api/authentication.py
mcp_formio_server/api/common.py
mcp_formio_server/api/form.py
mcp_formio_server/api/role.py
mcp_formio_server/api/submission.py
mcp_formio_server-0.1.5.dist-info/METADATA
mcp_formio_server-0.1.5.dist-info/WHEEL
mcp_formio_server-0.1.5.dist-info/entry_points.txt
mcp_formio_server-0.1.5.dist-info/licenses/LICENSE
mcp_formio_server-0.1.5.dist-info/RECORD
