Metadata-Version: 2.4
Name: mcp-formio-server
Version: 0.1.5
Summary: An MCP server for interacting with the FormIO API via Model Context Protocol tools, providing access to forms, submissions, roles, and user management.
Author-email: Damyan Dimitrov <inspirationalcode@gmail.com>
Maintainer: MCP-FORGE
License-File: LICENSE
Keywords: ai,automation,formio,forms,llm,mcp,roles,submissions
Classifier: Development Status :: 4 - Beta
Classifier: Environment :: Console
Classifier: Intended Audience :: Developers
Classifier: License :: OSI Approved :: MIT License
Classifier: Operating System :: OS Independent
Classifier: Programming Language :: Python :: 3
Classifier: Programming Language :: Python :: 3.13
Classifier: Topic :: Software Development :: Libraries
Classifier: Topic :: Utilities
Requires-Python: >=3.13
Requires-Dist: httpx>=0.28.1
Requires-Dist: mcp[cli]>=1.8.1
